etc/raspberrylink-server.conf
opt/raspberrylink/raspilink-bt-agent.py
opt/raspberrylink/raspilink-bt-init
opt/raspberrylink/service-files/raspberrylink
opt/raspberrylink/service-files/raspberrylink-agent.service
opt/raspberrylink/service-files/raspberrylink-diskless-init
opt/raspberrylink/service-files/raspberrylink.service
raspberrylink/__init__.py
raspberrylink/agent.py
raspberrylink/config.py
raspberrylink/server.py
raspberrylink/audio/__init__.py
raspberrylink/audio/core.py
raspberrylink/audio/handsfree.py
raspberrylink/audio/routing.py
raspberrylink-2.2.1.dist-info/LICENSE
raspberrylink-2.2.1.dist-info/METADATA
raspberrylink-2.2.1.dist-info/WHEEL
raspberrylink-2.2.1.dist-info/entry_points.txt
raspberrylink-2.2.1.dist-info/top_level.txt
raspberrylink-2.2.1.dist-info/RECORD
