Metadata-Version: 2.1
Name: raspberrylink
Version: 2.2.1
Summary: Handsfree bluetooth audio server for use in a car on a Raspberry Pi
Home-page: https://github.com/jython234/raspberry-link
Author: jython234
Author-email: jython234@gmail.com
License: MPL-2.0
Platform: UNKNOWN
Requires-Python: >=3.6
Requires-Dist: flask
Requires-Dist: waitress
Requires-Dist: dbus-python
Requires-Dist: PyGObject
